concretefhe_backend-0.0.10-py3.9-nspkg.pth
concretefhe/backend/__init__.py
concretefhe/backend/file.py
concretefhe_backend-0.0.10.dist-info/LICENSE
concretefhe_backend-0.0.10.dist-info/METADATA
concretefhe_backend-0.0.10.dist-info/WHEEL
concretefhe_backend-0.0.10.dist-info/namespace_packages.txt
concretefhe_backend-0.0.10.dist-info/top_level.txt
concretefhe_backend-0.0.10.dist-info/RECORD
